earendil/__init__.py
earendil/ircdef/__init__.py
earendil/ircdef/__main__.py
earendil/ircdef/messages.desc
earendil/ircdef/mkdocs.py
earendil/ircdef/parser.py
earendil/ircdef/template.py
earendil/ircdef/formats/markdown.md
earendil-0.1.dist-info/LICENSE.md
earendil-0.1.dist-info/METADATA
earendil-0.1.dist-info/WHEEL
earendil-0.1.dist-info/entry_points.txt
earendil-0.1.dist-info/top_level.txt
earendil-0.1.dist-info/RECORD
