Metadata-Version: 2.1
Name: earendil
Version: 0.1
Summary: machine-readable IRC protocol specification
Home-page: https://github.com/agrif/earendil/
Author: Aaron Griffith
Author-email: aargri@gmail.com
License: MIT
Project-URL: Source, https://github.com/agrif/earendil/
Project-URL: Documentation, https://earendil-irc.readthedocs.io/en/latest/
Keywords: irc specification
Platform: any
Classifier: Development Status :: 4 - Beta
Classifier: Intended Audience :: Developers
Classifier: Topic :: Software Development :: Libraries :: Python Modules
Classifier: License :: OSI Approved :: MIT License
Classifier: Programming Language :: Python :: 3
Requires-Python: >=3.5
Requires-Dist: lark-parser (>=0.8.0)
Requires-Dist: jinja2 (>=2.10.0)
Requires-Dist: markdown (>=3.2.0)
Provides-Extra: docs
Requires-Dist: mkdocs (>=1.0) ; extra == 'docs'
Requires-Dist: mkautodoc (>=0.1.0) ; extra == 'docs'
